simpleanalytics/__init__.py
simpleanalytics/templatetags/__init__.py
simpleanalytics/templatetags/simpleanalytics_tags.py
simpleanalytics-1.0.7.dist-info/LICENSE
simpleanalytics-1.0.7.dist-info/METADATA
simpleanalytics-1.0.7.dist-info/WHEEL
simpleanalytics-1.0.7.dist-info/top_level.txt
simpleanalytics-1.0.7.dist-info/RECORD
