Metadata-Version: 2.1
Name: simpleanalytics
Version: 1.0.7
Summary: Simple Analytics template tags for Django
Home-page: https://github.com/simpleanalytics/django-plugin
Author: Simple Analytics
Author-email: noreply@simpleanalytics.com
Classifier: Development Status :: 3 - Alpha
Classifier: Intended Audience :: Developers
Classifier: Environment :: Plugins
Classifier: License :: OSI Approved :: MIT License
Classifier: Programming Language :: Python
Classifier: Programming Language :: Python :: 3.5
Classifier: Programming Language :: Python :: 3.6
Classifier: Programming Language :: Python :: 3.7
Classifier: Topic :: Internet :: WWW/HTTP :: Dynamic Content :: Page Counters
Classifier: Framework :: Django :: 2.0
Classifier: Framework :: Django :: 2.1
Classifier: Framework :: Django :: 2.2
Classifier: Framework :: Django :: 3.0
License-File: LICENSE
Requires-Dist: Django >=2.0
